LICENSE.txt
MANIFEST.in
README.md
setup.cfg
setup.py
./LICENSE.txt
./README.md
./setup.py
./SRPREM/GetObj.py
./SRPREM/GetREMOffsets.py
./SRPREM/GetREMSite.py
./SRPREM/__init__.py
./SRPREM/PM/Classic.py
./SRPREM/PM/Extra.py
./SRPREM/PM/FindOrigCoord.py
./SRPREM/PM/Full.py
./SRPREM/PM/Simple.py
./SRPREM/PM/__init__.py
./SRPREM/PM/minClassic.py
./SRPREM/PM/minExtra.py
./SRPREM/PM/minFull.py
./SRPREM/PM/minSimple.py
./build/lib/SRPREM/GetObj.py
./build/lib/SRPREM/GetREMOffsets.py
./build/lib/SRPREM/GetREMSite.py
./build/lib/SRPREM/__init__.py
./build/lib/SRPREM/PM/Classic.py
./build/lib/SRPREM/PM/Extra.py
./build/lib/SRPREM/PM/FindOrigCoord.py
./build/lib/SRPREM/PM/Full.py
./build/lib/SRPREM/PM/Simple.py
./build/lib/SRPREM/PM/__init__.py
./build/lib/SRPREM/PM/minClassic.py
./build/lib/SRPREM/PM/minExtra.py
./build/lib/SRPREM/PM/minFull.py
./build/lib/SRPREM/PM/minSimple.py
Docs/SRPAstro.REM.pdf
SRPAstro.REM.egg-info/PKG-INFO
SRPAstro.REM.egg-info/PKG-INFO_conflict-20171114-155554
SRPAstro.REM.egg-info/SOURCES.txt
SRPAstro.REM.egg-info/dependency_links.txt
SRPAstro.REM.egg-info/requires.txt
SRPAstro.REM.egg-info/requires_conflict-20171114-155554.txt
SRPAstro.REM.egg-info/top_level.txt
SRPREM/GetObj.py
SRPREM/GetREMOffsets.py
SRPREM/GetREMSite.py
SRPREM/__init__.py
SRPREM/PM/Classic.py
SRPREM/PM/Extra.py
SRPREM/PM/FindOrigCoord.py
SRPREM/PM/Full.py
SRPREM/PM/Simple.py
SRPREM/PM/__init__.py
SRPREM/PM/minClassic.py
SRPREM/PM/minExtra.py
SRPREM/PM/minFull.py
SRPREM/PM/minSimple.py
Scripts/SRPMyPhotometry
Scripts/SRPREMAstrometry
Scripts/SRPREMAstrometryDeep
Scripts/SRPREMAstrometrySearch
Scripts/SRPREMDataBase
Scripts/SRPREMOffsets
Scripts/SRPREMPhotometry
Scripts/SRPREMPointingModel
Scripts/SRPREMVersion